src/ALU.sv
module ALU (
    input logic [31:0] src1, src2,

    // 4 bits for 16 ALU functions
    input logic [3:0] alu_ctrl,

    output logic [31:0] result
);

    typedef enum logic [3:0] {
        ADD  = 4'b0000,
        SUB  = 4'b0001,
        XOR  = 4'b0010,
        OR   = 4'b0011,
        AND  = 4'b0100,
        SLL  = 4'b0101,
        SRL  = 4'b0110,
        SRA  = 4'b0111,
        SLT  = 4'b1000,
        SLTU = 4'b1001,
        JALR = 4'b1010,
        THRU = 4'b1111
    } alu_codes; 
    

    always_comb begin
        case (alu_ctrl)
            ADD : result = src1 + src2;
            SUB : result = src1 + (~src2 + 1'b1);
            XOR : result = src1 ^ src2;
            OR  : result = src1 | src2;
            AND : result = src1 & src2;
            SLL : result = src1 << src2[4:0];
            SRL : result = src1 >> src2[4:0];
            SRA : result = $signed(src1) >>> src2[4:0];
            SLT : result = {31'b0, $signed(src1) < $signed(src2)};
            SLTU: result = {31'b0, src1 < src2};
            JALR: result = (src1 + src2) & ~1;
            THRU: result = src2;
            default: result = 32'd0;
        endcase
    end
    
endmodule

src/ALU_waveform.vcd
$version Generated by VerilatedVcd $end
$timescale 1ps $end
 $scope module TOP $end
  $var wire 32 # src1 [31:0] $end
  $var wire 32 $ src2 [31:0] $end
  $var wire 4 % alu_ctrl [3:0] $end
  $var wire 32 & result [31:0] $end
  $scope module ALU $end
   $var wire 32 # src1 [31:0] $end
   $var wire 32 $ src2 [31:0] $end
   $var wire 4 % alu_ctrl [3:0] $end
   $var wire 32 & result [31:0] $end
  $upscope $end
 $upscope $end
$enddefinitions $end


#0
b01101011100010110100010101100111 #
b00110010011110110010001111000110 $
b0000 %
b10011110000001100110100100101101 &
#1
b01100100001111001001100001101001 #
b01100110001100110100100001110011 $
b11001010011011111110000011011100 &
#2
b01110100101100001101110001010001 #
b00011001010010010101110011111111 $
b10001101111110100011100101010000 &
#3
b00101010111010001001010001001010 #
b01100010010101010101100011101100 $
b10001101001111011110110100110110 &
#4
b00100011100011100001111100101001 #
b01000110111010000111110011001101 $
b01101010011101101001101111110110 &
#5
b00111101000110110101100010111010 #
b01010000011111101101011110101011 $
b0001 %
b11101100100111001000000100001111 &
#6
b00101110101100010100000111110010 #
b01000001101101110001111011111011 $
b11101100111110100010001011110111 &
#7
b01111001111000101010100111100011 #
b01110101010001011110000101000110 $
b00000100100111001100100010011101 &
#8
b01010001010111110000000001111100 #
b01011011110100000110001011000010 $
b11110101100011101001110110111010 &
#9
b00010010001000000000100001010100 #
b01001101101100010010011111111000 $
b11000100011011101110000001011100 &
#10
b00000010000101100010001100011011 #
b00011111000101101110100111101000 $
b0010 %
b00011101000000001100101011110011 &
#11
b00010001100100001100110111100111 #
b01100110111011110100001110001101 $
b01110111011111111000111001101010 &
#12
b00010100000011100000111101110110 #
b00110011010100100010010101011010 $
b00100111010111000010101000101100 &
#13
b00010000100111001111100100101110 #
b00001101111011010111001001100011 $
b00011101011100011000101101001101 &
#14
b01111111110111001100001000110011 #
b00011011111011111101011110011111 $
b01100100001100110001010110101100 &
#15
b01000001101001111100010011001001 #
b01101011011010000000011110011010 $
b0011 %
b01101011111011111100011111011011 &
#16
b01001110011010101111101101100110 #
b00100101111001000101110100110010 $
b01101111111011101111111101110110 &
#17
b01010001100110110101000000001101 #
b01000011000110111101011110110111 $
b01010011100110111101011110111111 &
#18
b00111111001011011011101000110001 #
b01111100100000111110010001011000 $
b01111111101011111111111001111001 &
#19
b00100101011100010011000010100011 #
b01100010101110111101100101011010 $
b01100111111110111111100111111011 &
#20
b01000011011011000110000100100101 #
b01100010100011001000100101011101 $
b0100 %
b01000010000011000000000100000101 &
#21
b00110011001110101011000100000101 #
b01110010000111011010001100010111 $
b00110010000110001010000100000101 &
#22
b00100100010000111010100001011000 #
b00101101000111010101101011101001 $
b00100100000000010000100001001000 &
#23
b01100111011000111000010001011110 #
b01110101101000101010100011010100 $
b01100101001000101000000001010100 &
#24
b00001000111011011011110110101011 #
b01111001100000111000110010110010 $
b00001000100000011000110010100010 &
#25
b01000011010100111101000011001101 #
b00001011000000111110000011000110 $
b0101 %
b11010100111101000011001101000000 &
#26
b00011000100110100111011010011011 #
b01010100111001001001111010110100 $
b01101001101100000000000000000000 &
#27
b01110001111100110010010001010100 #
b00101100101010001000011000010001 $
b01001000101010000000000000000000 &
#28
b00001000001101101100010000001110 #
b00000010100100000001110110000010 $
b00100000110110110001000000111000 &
#29
b00111010100101011111100001110100 #
b00001000000100111000011001000001 $
b01110101001010111111000011101000 &
#30
b00011110011111111111010100100001 #
b01111100001111011011110100111101 $
b0110 %
b00000000000000000000000000000000 &
#31
b01110011011110111000110111011100 #
b01101100111010101111000010000111 $
b00000000111001101111011100011011 &
#32
b00100010001000100001101001110000 #
b01000101000101101101110111101001 $
b00000000000100010001000100001101 &
#33
b00110000000001101100100000111110 #
b01100001010011111101010010100001 $
b00011000000000110110010000011111 &
#34
b01000001100110101100001001000001 #
b01010101011101111111100011100001 $
b00100000110011010110000100100000 &
#35
b01000100000010111010110111111100 #
b00000101000001110010001101100111 $
b0111 %
b00000000100010000001011101011011 &
#36
b00111000000001001000001000111110 #
b01110111010001100101111100000001 $
b00011100000000100100000100011111 &
#37
b01110111001001001100011001111110 #
b01011100010010000010101010010111 $
b00000000000000000000000011101110 &
#38
b00100100011000111011100111101010 #
b01011110100010000100101011011100 $
b00000000000000000000000000000010 &
#39
b01010001111010101101001101101011 #
b00101101010100010111011110010110 $
b00000000000000000000000101000111 &
#40
b01011000000010111101011110001111 #
b00010101001111101010010000111000 $
b1000 %
b00000000000000000000000000000000 &
#41
b00111000010101010101100001011100 #
b01110000101001100100111000101010 $
b00000000000000000000000000000001 &
#42
b01101010001000110100001011101100 #
b00101010010010000111110010110000 $
b00000000000000000000000000000000 &
#43
b00011101010011101101010000111011 #
b01110010010110100000011011111011 $
b00000000000000000000000000000001 &
#44
b00101100110110001001101000110010 #
b01010111111001001100110010101111 $
#45
b01111010011011011000110100111100 #
b01001011010110001000111101010100 $
b1001 %
b00000000000000000000000000000000 &
#46
b01010100001000101000100111101100 #
b01101101111010010001101100011000 $
b00000000000000000000000000000001 &
#47
b00111000010000110111111111011011 #
b01110110010001001010010001011100 $
#48
b00110010111111111111100100000010 #
b01101000010010100100100000011010 $
#49
b01010111100101000111100011111110 #
b01110100100110101011101101000011 $
#50
b00111101110000100100000011111011 #
b00011011101000000010011011111010 $
b1010 %
b01011001011000100110011111110100 &
#51
b01111001101000011101111010101010 #
b01110101110001101100001100111010 $
b11101111011010001010000111100100 &
#52
b00010010111001101000010111111011 #
b01110000110001101010010100101001 $
b10000011101011010010101100100100 &
#53
b01010010000011101110110111010001 #
b00110111010010100011111111100110 $
b10001001010110010010110110110110 &
#54
b01001111010011101111000000000101 #
b00100011111110011100000100111100 $
b01110011010010001011000101000000 &
#55
b01100100100110111011011101111100 #
b00100111010110101100011110010100 $
b1011 %
b00000000000000000000000000000000 &
#56
b00111001001110000110010101110101 #
b00011100111100010000111111011000 $
#57
b00011000000000010001010110111110 #
b00100011010110111010100001100001 $
#58
b01000111001110011000110010001001 #
b00110101010011111110100111111001 $
#59
b00010101101101011010111101011100 #
b01110100000100100010011010111011 $
#60
b00001101001101001011011010101000 #
b00010000001000110011110010011001 $
b1100 %
#61
b00111111011010101011011000001111 #
b01100001010101110100000010010101 $
#62
b01111110000011000101011110110001 #
b01110111101011100011010111101011 $
#63
b01010111100110111110010011110001 #
b00110001000011000101000010110011 $
#64
b01011111111110000111111000000101 #
b00101111001100000101110111101111 $
#65
b00100101101001110000101111110111 #
b00011101101110101011111100000000 $
b1101 %
#66
b01001010110100001000010011101001 #
b00011111010010001110101010100001 $
#67
b00010011100000011000001000111010 #
b01011101101101110000101011100101 $
#68
b00010000000011111000111111001010 #
b01100101100100000111000000001011 $
#69
b00010101000000010100101011001011 #
b01011111010111100111111111010000 $
#70
b00001001100010100011000101001000 #
b01111001100111010000001001000111 $
b1110 %
#71
b00000110101110010100011101100100 #
b01000010110000101001011010111101 $
#72
b00010110100011100001001000011111 #
b00011110101110100101110100100011 $
#73
b01100110000111100011111100011110 #
b01011101110001111001111010101000 $
#74
b01010100000010100100011100011100 #
b01111011110100111110111001111011 $
#75
b01010001110110011100010101100100 #
b01100001001111101111110111000101 $
b1111 %
b01100001001111101111110111000101 &
#76
b00001011111101110010101100010100 #
b00010001010001000111101101110011 $
b00010001010001000111101101110011 &
#77
b01000010100101100011111001011010 #
b00001010000000111000001011000101 $
b00001010000000111000001011000101 &
#78
b00001000111100101011000101011110 #
b00011010001100100010001101001011 $
b00011010001100100010001101001011 &
#79
b00111011000011111101001101111001 #
b01101000111010110010111101100011 $
b01101000111010110010111101100011 &
