src/ImmGen.sv
module ImmGen (
    /* verilator lint_off UNUSEDSIGNAL */
    input logic [31:0] instr,
    /* verilator lint_on UNUSEDSIGNAL */
    output logic [31:0] immediate
);
    logic [4:0] opcode;
    logic [2:0] func3;

    localparam I_type      = 5'b00100;
    localparam B_type      = 5'b11000;
    localparam JAL_instr   = 5'b11011;
    localparam JALR_instr  = 5'b11001;
    localparam L_type      = 5'b00000;
    localparam S_type      = 5'b01000;
    localparam LUI_instr   = 5'b01101;
    localparam AUIPC_instr = 5'b00101;
    
    always_comb begin
        opcode = instr[6:2];
        func3  = instr[14:12];

        case (opcode)
            I_type : begin
                // if SHIFT operation
                if(func3 == 3'b001 || func3 == 3'b101)
                    immediate = {27'b0, instr[24:20]};
                else
                    immediate = {{20{instr[31]}}, instr[31:20]};
            end
            B_type:
                immediate = {{19{instr[31]}}, instr[31], instr[7], instr[30:25], instr[11:8], 1'b0};
            JALR_instr, L_type:
                immediate = {{20{instr[31]}}, instr[31:20]};
            JAL_instr:
                immediate = {{11{instr[31]}}, instr[31], instr[19:12], instr[20], instr[30:21], 1'b0};
            S_type:
                immediate = {{20{instr[31]}}, instr[31:25], instr[11:7]};
            LUI_instr, AUIPC_instr:
                immediate = {instr[31:12], 12'b0};            
            default: immediate = 32'b0;
        endcase
    end
endmodule

src/ImmGen_waveform.vcd
$version Generated by VerilatedVcd $end
$timescale 1ps $end
 $scope module TOP $end
  $var wire 32 # instr [31:0] $end
  $var wire 32 $ immediate [31:0] $end
  $scope module ImmGen $end
   $var wire 32 # instr [31:0] $end
   $var wire 32 $ immediate [31:0] $end
   $var wire 5 % opcode [4:0] $end
   $var wire 3 & func3 [2:0] $end
   $var wire 5 ' I_type [4:0] $end
   $var wire 5 ( B_type [4:0] $end
   $var wire 5 ) JAL_instr [4:0] $end
   $var wire 5 * JALR_instr [4:0] $end
   $var wire 5 + L_type [4:0] $end
   $var wire 5 , S_type [4:0] $end
   $var wire 5 - LUI_instr [4:0] $end
   $var wire 5 . AUIPC_instr [4:0] $end
  $upscope $end
 $upscope $end
$enddefinitions $end


#0
b00000000000100000000000010010011 #
b00000000000000000000000000000001 $
b00100 %
b000 &
b00100 '
b11000 (
b11011 )
b11001 *
b00000 +
b01000 ,
b01101 -
b00101 .
#1
b11111111111100000000000010010011 #
b11111111111111111111111111111111 $
#2
b00000000010100000000000010010011 #
b00000000000000000000000000000101 $
#3
b00000000010100000001100010010011 #
b001 &
#4
b01000000101000000101100010010011 #
b00000000000000000000000000001010 $
b101 &
#5
b00000000000100011000000000100011 #
b00000000000000000000000000000000 $
b01000 %
b000 &
#6
b11111110000100011001010010100011 #
b11111111111111111111111111101001 $
b001 &
#7
b01111110000100011001010010100011 #
b00000000000000000000011111101001 $
#8
b01111110000100011000010010000011 #
b00000000000000000000011111100001 $
b00000 %
b000 &
#9
b11100110000100011101010010000011 #
b11111111111111111111111001100001 $
b101 &
#10
b00000000000100011100010010000011 #
b00000000000000000000000000000001 $
b100 &
#11
b00000000000100100000000011100011 #
b00000000000000000000100000000000 $
b11000 %
b000 &
#12
b01010100000100100100101011100011 #
b00000000000000000000110101010100 $
b100 &
#13
b11111110000100100001111111100011 #
b11111111111111111111111111111110 $
b001 &
#14
b10101110101101011100010011101111 #
b11111111111101011100101011101010 $
b11011 %
b100 &
#15
b11111110111110011000010011100111 #
b11111111111111111111111111101111 $
b11001 %
b000 &
#16
b11111111110010111011000100110111 #
b11111111110010111011000000000000 $
b01101 %
b011 &
#17
b00000000010100000100000100010111 #
b00000000010100000100000000000000 $
b00101 %
b100 &
