src/InstrMem.sv
module InstrMem#(
    parameter WORDS = 128,
    parameter mem_init = "InstrMem_test.mem"
) (
    input logic clk,
    input logic [31:0] address,
    output logic [31:0] instr
);

    // Memory array: stores bytes, total size is WORDS * 4 bytes
    reg [7:0] mem[0:(WORDS * 4) - 1];

    initial begin
        if (mem_init != "") begin
            // Load memory contents from a hex file
            $readmemh(mem_init, mem);
        end else begin
            // Otherwise, initialize all memory locations to zero
            for (int i = 0; i < (WORDS * 4); i = i + 1) begin
                mem[i] = 8'h00;
            end
        end
    end

    always_ff @(posedge clk ) begin
        // Asynchronous read w/ EOF Flag
        instr <= (address + 3) >= (WORDS * 4) ? 32'hDEADBEEF : {mem[address + 0],
                                                                mem[address + 1],
                                                                mem[address + 2],
                                                                mem[address + 3]};
    end

endmodule

src/InstrMem_waveform.vcd
$version Generated by VerilatedVcd $end
$timescale 1ps $end
 $scope module TOP $end
  $var wire 1 # clk $end
  $var wire 32 $ address [31:0] $end
  $var wire 32 % instr [31:0] $end
  $scope module InstrMem $end
   $var wire 32 & WORDS [31:0] $end
   $var wire 136 ' mem_init [135:0] $end
   $var wire 1 # clk $end
   $var wire 32 $ address [31:0] $end
   $var wire 32 % instr [31:0] $end
  $upscope $end
 $upscope $end
$enddefinitions $end


#0
0#
b00000000000000000000000000000100 $
b00000000000000000000000000000000 %
b00000000000000000000000010000000 &
b0100100101101110011100110111010001110010010011010110010101101101010111110111010001100101011100110111010000101110011011010110010101101101 '
#1
1#
b00010010001101000101011001111000 %
#2
0#
b00000000000000000000000000000000 $
#3
1#
b00000000000000000000000000000000 %
#4
0#
b00000000000000000000000000001000 $
#5
1#
b10101010101110111100110011011101 %
#6
0#
b00000000000000000000000000001100 $
#7
1#
b00000000000000000000000000001100 %
#8
0#
b00000000000000000000000000100000 $
#9
1#
b00000000000000000000000000000000 %
#10
0#
b00000000000000000000000111111100 $
#11
1#
#12
0#
b00000000000000000000001000000000 $
#13
1#
b11011110101011011011111011101111 %
#14
0#
b00000000000000000000001000000100 $
