RegFile.sv
// Name    |   ABI Mnemonic   |   Meaning            |   Preserved across calls?
// --------|------------------|----------------------|-------------------------------------------------------------
// x0      |   zero           |   Zero               |   (Immutable)
// x1      |   ra             |   Return addr        |   No
// x2      |   sp             |   Stack ptr          |   Yes
// x3      |   gp             |   Global ptr         |   (Unallocatable)
// x4      |   tp             |   Thread ptr         |   (Unallocatable)
// x5-x7   |   t0-t2          |   Temp regs          |   No
// x8-x9   |   s0-s1          |   Callee-Saved regs  |   Yes
// x10-x17 |   a0-a7          |   Arg regs           |   No
// x18-x27 |   s2-s11         |   Callee-Saved regs  |   Yes
// x28-x31 |   t3-t6          |   Temp regs          |   No

module RegFile (
    input clk, rst, wen,
    input [4:0] rsrc1, rsrc2, wdest,
    input [31:0] wdata,

    output [31:0] rdata1, rdata2
);
    reg [31:0] regs [0:31]; //32 32-bit Registers
    initial regs[0] = 0;

    always_ff @(posedge clk) begin
        if (!rst) begin
            for (int i = 0; i < 32; i = i + 1)begin
                regs[i] <= 32'b0;
            end
        end else if (wen && wdest != 5'b0)
            regs[wdest] <= wdata;
    end

    // Asynchronous reads with write forwarding
    assign rdata1 = (wen && (rsrc1 == wdest) && wdest != 5'd0) ? wdata : regs[rsrc1];
    assign rdata2 = (wen && (rsrc2 == wdest) && wdest != 5'd0) ? wdata : regs[rsrc2];

endmodule

src/RegFile_waveform.vcd
$version Generated by VerilatedVcd $end
$timescale 1ps $end
 $scope module TOP $end
  $var wire 1 D clk $end
  $var wire 1 E rst $end
  $var wire 1 F wen $end
  $var wire 5 G rsrc1 [4:0] $end
  $var wire 5 H rsrc2 [4:0] $end
  $var wire 5 I wdest [4:0] $end
  $var wire 32 J wdata [31:0] $end
  $var wire 32 K rdata1 [31:0] $end
  $var wire 32 L rdata2 [31:0] $end
  $scope module RegFile $end
   $var wire 1 D clk $end
   $var wire 1 E rst $end
   $var wire 1 F wen $end
   $var wire 5 G rsrc1 [4:0] $end
   $var wire 5 H rsrc2 [4:0] $end
   $var wire 5 I wdest [4:0] $end
   $var wire 32 J wdata [31:0] $end
   $var wire 32 K rdata1 [31:0] $end
   $var wire 32 L rdata2 [31:0] $end
   $var wire 32 # regs[0] [31:0] $end
   $var wire 32 $ regs[1] [31:0] $end
   $var wire 32 % regs[2] [31:0] $end
   $var wire 32 & regs[3] [31:0] $end
   $var wire 32 ' regs[4] [31:0] $end
   $var wire 32 ( regs[5] [31:0] $end
   $var wire 32 ) regs[6] [31:0] $end
   $var wire 32 * regs[7] [31:0] $end
   $var wire 32 + regs[8] [31:0] $end
   $var wire 32 , regs[9] [31:0] $end
   $var wire 32 - regs[10] [31:0] $end
   $var wire 32 . regs[11] [31:0] $end
   $var wire 32 / regs[12] [31:0] $end
   $var wire 32 0 regs[13] [31:0] $end
   $var wire 32 1 regs[14] [31:0] $end
   $var wire 32 2 regs[15] [31:0] $end
   $var wire 32 3 regs[16] [31:0] $end
   $var wire 32 4 regs[17] [31:0] $end
   $var wire 32 5 regs[18] [31:0] $end
   $var wire 32 6 regs[19] [31:0] $end
   $var wire 32 7 regs[20] [31:0] $end
   $var wire 32 8 regs[21] [31:0] $end
   $var wire 32 9 regs[22] [31:0] $end
   $var wire 32 : regs[23] [31:0] $end
   $var wire 32 ; regs[24] [31:0] $end
   $var wire 32 < regs[25] [31:0] $end
   $var wire 32 = regs[26] [31:0] $end
   $var wire 32 > regs[27] [31:0] $end
   $var wire 32 ? regs[28] [31:0] $end
   $var wire 32 @ regs[29] [31:0] $end
   $var wire 32 A regs[30] [31:0] $end
   $var wire 32 B regs[31] [31:0] $end
   $scope module unnamedblk1 $end
    $var wire 32 C i [31:0] $end
   $upscope $end
  $upscope $end
 $upscope $end
$enddefinitions $end


#0
b00000000000000000000000000000000 #
b00000000000000000000000000000000 $
b00000000000000000000000000000000 %
b00000000000000000000000000000000 &
b00000000000000000000000000000000 '
b00000000000000000000000000000000 (
b00000000000000000000000000000000 )
b00000000000000000000000000000000 *
b00000000000000000000000000000000 +
b00000000000000000000000000000000 ,
b00000000000000000000000000000000 -
b00000000000000000000000000000000 .
b00000000000000000000000000000000 /
b00000000000000000000000000000000 0
b00000000000000000000000000000000 1
b00000000000000000000000000000000 2
b00000000000000000000000000000000 3
b00000000000000000000000000000000 4
b00000000000000000000000000000000 5
b00000000000000000000000000000000 6
b00000000000000000000000000000000 7
b00000000000000000000000000000000 8
b00000000000000000000000000000000 9
b00000000000000000000000000000000 :
b00000000000000000000000000000000 ;
b00000000000000000000000000000000 <
b00000000000000000000000000000000 =
b00000000000000000000000000000000 >
b00000000000000000000000000000000 ?
b00000000000000000000000000000000 @
b00000000000000000000000000000000 A
b00000000000000000000000000000000 B
b00000000000000000000000000000000 C
0D
0E
0F
b00001 G
b00010 H
b00001 I
b00000000000000000000000000000000 J
b00000000000000000000000000000000 K
b00000000000000000000000000000000 L
#1
b00000000000000000000000000100000 C
1D
#2
0D
1E
1F
b00010010001101000101011001111000 J
b00010010001101000101011001111000 K
#3
b00010010001101000101011001111000 $
1D
#4
0D
0F
b00010 I
#5
1D
#6
0D
1F
b00000 G
b01010 H
b00000 I
b11011110101011011011111011101111 J
b00000000000000000000000000000000 K
#7
1D
#8
0D
b00001 G
b00010 H
b00010 I
b00010010001101000101011001111000 K
b11011110101011011011111011101111 L
#9
b11011110101011011011111011101111 %
1D
#10
0D
b01101 G
b11111 H
b10000 I
b00010110000101100001011000010110 J
b00000000000000000000000000000000 K
b00000000000000000000000000000000 L
#11
b00010110000101100001011000010110 3
1D
#12
0D
0E
0F
b10000 G
b00010 H
b11011110101011011011111011101111 J
b00010110000101100001011000010110 K
b11011110101011011011111011101111 L
#13
b00000000000000000000000000000000 $
b00000000000000000000000000000000 %
b00000000000000000000000000000000 3
1D
b00000000000000000000000000000000 K
b00000000000000000000000000000000 L
