src/ALU.sv
module ALU (
    input logic [31:0]  rdata1, rdata2, pc, imm,
    // 4 bits for 16 ALU functions
    input logic [3:0]   alu_ctrl,
    input logic         pc_sel, imm_sel,
    output logic [31:0] result
);
    /* verilator lint_off UNOPTFLAT */
    logic [31:0] src1, src2;
    /* verilator lint_on UNOPTFLAT */

    assign src1 = pc_sel  ? pc  : rdata1;
    assign src2 = imm_sel ? imm : rdata2;

    // Mostly {Func3, fun7[6]}
    typedef enum logic [3:0] {
        ADD  = 4'b0000,
        SUB  = 4'b0001,
        SLT  = 4'b0100,
        SLTU = 4'b0110,
        XOR  = 4'b1000,
        OR   = 4'b1100,
        AND  = 4'b1110,
        SLL  = 4'b0010,
        SRA  = 4'b1011,
        SRL  = 4'b1010,
        JALR = 4'b0011,
        THRU = 4'b1111
    } alu_codes; 

    always_comb begin
        case (alu_ctrl)
            ADD : result = src1 + src2;
            SUB : result = src1 + (~src2 + 1'b1);
            XOR : result = src1 ^ src2;
            OR  : result = src1 | src2;
            AND : result = src1 & src2;
            SLL : result = src1 << src2[4:0];
            SRL : result = src1 >> src2[4:0];
            SRA : result = $signed(src1) >>> src2[4:0];
            SLT : result = {31'b0, $signed(src1) < $signed(src2)};
            SLTU: result = {31'b0, src1 < src2};
            JALR: result = (src1 + src2) & ~32'b1;
            default: result = src2; // THRU
        endcase
    end

endmodule

VCD/ALU_waveform.vcd
$version Generated by VerilatedVcd $end
$timescale 1ps $end
 $scope module TOP $end
  $var wire 32 # rdata1 [31:0] $end
  $var wire 32 $ rdata2 [31:0] $end
  $var wire 32 % pc [31:0] $end
  $var wire 32 & imm [31:0] $end
  $var wire 4 ' alu_ctrl [3:0] $end
  $var wire 1 ( pc_sel $end
  $var wire 1 ) imm_sel $end
  $var wire 32 * result [31:0] $end
  $scope module ALU $end
   $var wire 32 # rdata1 [31:0] $end
   $var wire 32 $ rdata2 [31:0] $end
   $var wire 32 % pc [31:0] $end
   $var wire 32 & imm [31:0] $end
   $var wire 4 ' alu_ctrl [3:0] $end
   $var wire 1 ( pc_sel $end
   $var wire 1 ) imm_sel $end
   $var wire 32 * result [31:0] $end
   $var wire 32 + src1 [31:0] $end
   $var wire 32 , src2 [31:0] $end
  $upscope $end
 $upscope $end
$enddefinitions $end


#0
b01101011100010110100010101100111 #
b00110010011110110010001111000110 $
b00000000000000000000000000000000 %
b00000000000000000000000000000000 &
b0000 '
0(
0)
b10011110000001100110100100101101 *
b01101011100010110100010101100111 +
b00110010011110110010001111000110 ,
#1
b00000000000000000000000000000000 #
b01100110001100110100100001110011 $
b01100100001111001001100001101001 %
1(
b11001010011011111110000011011100 *
b01100100001111001001100001101001 +
b01100110001100110100100001110011 ,
#2
b01110100101100001101110001010001 #
b00000000000000000000000000000000 $
b00000000000000000000000000000000 %
b00011001010010010101110011111111 &
0(
1)
b10001101111110100011100101010000 *
b01110100101100001101110001010001 +
b00011001010010010101110011111111 ,
#3
b00101010111010001001010001001010 #
b01100010010101010101100011101100 $
b00000000000000000000000000000000 &
b0001 '
0)
b11001000100100110011101101011110 *
b00101010111010001001010001001010 +
b01100010010101010101100011101100 ,
#4
b00000000000000000000000000000000 #
b01000110111010000111110011001101 $
b00100011100011100001111100101001 %
1(
b11011100101001011010001001011100 *
b00100011100011100001111100101001 +
b01000110111010000111110011001101 ,
#5
b00111101000110110101100010111010 #
b00000000000000000000000000000000 $
b00000000000000000000000000000000 %
b01010000011111101101011110101011 &
0(
1)
b11101100100111001000000100001111 *
b00111101000110110101100010111010 +
b01010000011111101101011110101011 ,
#6
b00101110101100010100000111110010 #
b01000001101101110001111011111011 $
b00000000000000000000000000000000 &
b0010 '
0)
b10010000000000000000000000000000 *
b00101110101100010100000111110010 +
b01000001101101110001111011111011 ,
#7
b00000000000000000000000000000000 #
b01110101010001011110000101000110 $
b01111001111000101010100111100011 %
1(
b01111000101010100111100011000000 *
b01111001111000101010100111100011 +
b01110101010001011110000101000110 ,
#8
b01010001010111110000000001111100 #
b00000000000000000000000000000000 $
b00000000000000000000000000000000 %
b01011011110100000110001011000010 &
0(
1)
b01000101011111000000000111110000 *
b01010001010111110000000001111100 +
b01011011110100000110001011000010 ,
#9
b00010010001000000000100001010100 #
b01001101101100010010011111111000 $
b00000000000000000000000000000000 &
b0011 '
0)
b01011111110100010011000001001100 *
b00010010001000000000100001010100 +
b01001101101100010010011111111000 ,
#10
b00000000000000000000000000000000 #
b00011111000101101110100111101000 $
b00000010000101100010001100011011 %
1(
b00100001001011010000110100000010 *
b00000010000101100010001100011011 +
b00011111000101101110100111101000 ,
#11
b00010001100100001100110111100111 #
b00000000000000000000000000000000 $
b00000000000000000000000000000000 %
b01100110111011110100001110001101 &
0(
1)
b01111000100000000001000101110100 *
b00010001100100001100110111100111 +
b01100110111011110100001110001101 ,
#12
b00010100000011100000111101110110 #
b00110011010100100010010101011010 $
b00000000000000000000000000000000 &
b0100 '
0)
b00000000000000000000000000000001 *
b00010100000011100000111101110110 +
b00110011010100100010010101011010 ,
#13
b00000000000000000000000000000000 #
b00001101111011010111001001100011 $
b00010000100111001111100100101110 %
1(
b00000000000000000000000000000000 *
b00010000100111001111100100101110 +
b00001101111011010111001001100011 ,
#14
b01111111110111001100001000110011 #
b00000000000000000000000000000000 $
b00000000000000000000000000000000 %
b00011011111011111101011110011111 &
0(
1)
b01111111110111001100001000110011 +
b00011011111011111101011110011111 ,
#15
b01000001101001111100010011001001 #
b01101011011010000000011110011010 $
b00000000000000000000000000000000 &
b0101 '
0)
b01101011011010000000011110011010 *
b01000001101001111100010011001001 +
b01101011011010000000011110011010 ,
#16
b00000000000000000000000000000000 #
b00100101111001000101110100110010 $
b01001110011010101111101101100110 %
1(
b00100101111001000101110100110010 *
b01001110011010101111101101100110 +
b00100101111001000101110100110010 ,
#17
b01010001100110110101000000001101 #
b00000000000000000000000000000000 $
b00000000000000000000000000000000 %
b01000011000110111101011110110111 &
0(
1)
b01000011000110111101011110110111 *
b01010001100110110101000000001101 +
b01000011000110111101011110110111 ,
#18
b00111111001011011011101000110001 #
b01111100100000111110010001011000 $
b00000000000000000000000000000000 &
b0110 '
0)
b00000000000000000000000000000001 *
b00111111001011011011101000110001 +
b01111100100000111110010001011000 ,
#19
b00000000000000000000000000000000 #
b01100010101110111101100101011010 $
b00100101011100010011000010100011 %
1(
b00100101011100010011000010100011 +
b01100010101110111101100101011010 ,
#20
b01000011011011000110000100100101 #
b00000000000000000000000000000000 $
b00000000000000000000000000000000 %
b01100010100011001000100101011101 &
0(
1)
b01000011011011000110000100100101 +
b01100010100011001000100101011101 ,
#21
b00110011001110101011000100000101 #
b01110010000111011010001100010111 $
b00000000000000000000000000000000 &
b0111 '
0)
b01110010000111011010001100010111 *
b00110011001110101011000100000101 +
b01110010000111011010001100010111 ,
#22
b00000000000000000000000000000000 #
b00101101000111010101101011101001 $
b00100100010000111010100001011000 %
1(
b00101101000111010101101011101001 *
b00100100010000111010100001011000 +
b00101101000111010101101011101001 ,
#23
b01100111011000111000010001011110 #
b00000000000000000000000000000000 $
b00000000000000000000000000000000 %
b01110101101000101010100011010100 &
0(
1)
b01110101101000101010100011010100 *
b01100111011000111000010001011110 +
b01110101101000101010100011010100 ,
#24
b00001000111011011011110110101011 #
b01111001100000111000110010110010 $
b00000000000000000000000000000000 &
b1000 '
0)
b01110001011011100011000100011001 *
b00001000111011011011110110101011 +
b01111001100000111000110010110010 ,
#25
b00000000000000000000000000000000 #
b00001011000000111110000011000110 $
b01000011010100111101000011001101 %
1(
b01001000010100000011000000001011 *
b01000011010100111101000011001101 +
b00001011000000111110000011000110 ,
#26
b00011000100110100111011010011011 #
b00000000000000000000000000000000 $
b00000000000000000000000000000000 %
b01010100111001001001111010110100 &
0(
1)
b01001100011111101110100000101111 *
b00011000100110100111011010011011 +
b01010100111001001001111010110100 ,
#27
b01110001111100110010010001010100 #
b00101100101010001000011000010001 $
b00000000000000000000000000000000 &
b1001 '
0)
b00101100101010001000011000010001 *
b01110001111100110010010001010100 +
b00101100101010001000011000010001 ,
#28
b00000000000000000000000000000000 #
b00000010100100000001110110000010 $
b00001000001101101100010000001110 %
1(
b00000010100100000001110110000010 *
b00001000001101101100010000001110 +
b00000010100100000001110110000010 ,
#29
b00111010100101011111100001110100 #
b00000000000000000000000000000000 $
b00000000000000000000000000000000 %
b00001000000100111000011001000001 &
0(
1)
b00001000000100111000011001000001 *
b00111010100101011111100001110100 +
b00001000000100111000011001000001 ,
#30
b00011110011111111111010100100001 #
b01111100001111011011110100111101 $
b00000000000000000000000000000000 &
b1010 '
0)
b00000000000000000000000000000000 *
b00011110011111111111010100100001 +
b01111100001111011011110100111101 ,
#31
b00000000000000000000000000000000 #
b01101100111010101111000010000111 $
b01110011011110111000110111011100 %
1(
b00000000111001101111011100011011 *
b01110011011110111000110111011100 +
b01101100111010101111000010000111 ,
#32
b00100010001000100001101001110000 #
b00000000000000000000000000000000 $
b00000000000000000000000000000000 %
b01000101000101101101110111101001 &
0(
1)
b00000000000100010001000100001101 *
b00100010001000100001101001110000 +
b01000101000101101101110111101001 ,
#33
b00110000000001101100100000111110 #
b01100001010011111101010010100001 $
b00000000000000000000000000000000 &
b1011 '
0)
b00011000000000110110010000011111 *
b00110000000001101100100000111110 +
b01100001010011111101010010100001 ,
#34
b00000000000000000000000000000000 #
b01010101011101111111100011100001 $
b01000001100110101100001001000001 %
1(
b00100000110011010110000100100000 *
b01000001100110101100001001000001 +
b01010101011101111111100011100001 ,
#35
b01000100000010111010110111111100 #
b00000000000000000000000000000000 $
b00000000000000000000000000000000 %
b00000101000001110010001101100111 &
0(
1)
b00000000100010000001011101011011 *
b01000100000010111010110111111100 +
b00000101000001110010001101100111 ,
#36
b00111000000001001000001000111110 #
b01110111010001100101111100000001 $
b00000000000000000000000000000000 &
b1100 '
0)
b01111111010001101101111100111111 *
b00111000000001001000001000111110 +
b01110111010001100101111100000001 ,
#37
b00000000000000000000000000000000 #
b01011100010010000010101010010111 $
b01110111001001001100011001111110 %
1(
b01111111011011001110111011111111 *
b01110111001001001100011001111110 +
b01011100010010000010101010010111 ,
#38
b00100100011000111011100111101010 #
b00000000000000000000000000000000 $
b00000000000000000000000000000000 %
b01011110100010000100101011011100 &
0(
1)
b01111110111010111111101111111110 *
b00100100011000111011100111101010 +
b01011110100010000100101011011100 ,
#39
b01010001111010101101001101101011 #
b00101101010100010111011110010110 $
b00000000000000000000000000000000 &
b1101 '
0)
b00101101010100010111011110010110 *
b01010001111010101101001101101011 +
b00101101010100010111011110010110 ,
#40
b00000000000000000000000000000000 #
b00010101001111101010010000111000 $
b01011000000010111101011110001111 %
1(
b00010101001111101010010000111000 *
b01011000000010111101011110001111 +
b00010101001111101010010000111000 ,
#41
b00111000010101010101100001011100 #
b00000000000000000000000000000000 $
b00000000000000000000000000000000 %
b01110000101001100100111000101010 &
0(
1)
b01110000101001100100111000101010 *
b00111000010101010101100001011100 +
b01110000101001100100111000101010 ,
#42
b01101010001000110100001011101100 #
b00101010010010000111110010110000 $
b00000000000000000000000000000000 &
b1110 '
0)
b00101010000000000100000010100000 *
b01101010001000110100001011101100 +
b00101010010010000111110010110000 ,
#43
b00000000000000000000000000000000 #
b01110010010110100000011011111011 $
b00011101010011101101010000111011 %
1(
b00010000010010100000010000111011 *
b00011101010011101101010000111011 +
b01110010010110100000011011111011 ,
#44
b00101100110110001001101000110010 #
b00000000000000000000000000000000 $
b00000000000000000000000000000000 %
b01010111111001001100110010101111 &
0(
1)
b00000100110000001000100000100010 *
b00101100110110001001101000110010 +
b01010111111001001100110010101111 ,
#45
b01111010011011011000110100111100 #
b01001011010110001000111101010100 $
b00000000000000000000000000000000 &
b1111 '
0)
b01001011010110001000111101010100 *
b01111010011011011000110100111100 +
b01001011010110001000111101010100 ,
#46
b00000000000000000000000000000000 #
b01101101111010010001101100011000 $
b01010100001000101000100111101100 %
1(
b01101101111010010001101100011000 *
b01010100001000101000100111101100 +
b01101101111010010001101100011000 ,
#47
b00111000010000110111111111011011 #
b00000000000000000000000000000000 $
b00000000000000000000000000000000 %
b01110110010001001010010001011100 &
0(
1)
b01110110010001001010010001011100 *
b00111000010000110111111111011011 +
b01110110010001001010010001011100 ,
