src/BranchHandler.sv
module BranchHandler (
    input logic [2:0]   branch_cond,
    input logic [31:0]  src1, src2,
    output logic branched
);

logic equal, slt, sltu;

    // Func3 aside from NOB and JMP
    typedef enum logic [2:0] {
        NOB  = 3'b010,
        BEQ  = 3'b000,
        BNE  = 3'b001,
        BLT  = 3'b100,
        BGE  = 3'b101,
        BLTU = 3'b110,
        BGEU = 3'b111,
        JMP  = 3'b011
    } branch_codes;

    always_comb begin 
        equal = (src1 == src2);
        slt  = $signed(src1) < $signed(src2);
        sltu = src1 < src2;

        branched = 0;

        case(branch_cond)
            BEQ : branched = equal;
            BNE : branched = !equal;
            BLT : branched = slt;
            BGE : branched = !slt;
            BLTU: branched = sltu;
            BGEU: branched = !sltu;
            JMP : branched = 1;
            default: branched = 0;
        endcase
    end


endmodule

VCD/BranchHandler_waveform.vcd
$version Generated by VerilatedVcd $end
$timescale 1ps $end
 $scope module TOP $end
  $var wire 3 & branch_cond [2:0] $end
  $var wire 32 ' src1 [31:0] $end
  $var wire 32 ( src2 [31:0] $end
  $var wire 1 ) branched $end
  $scope module BranchHandler $end
   $var wire 3 & branch_cond [2:0] $end
   $var wire 32 ' src1 [31:0] $end
   $var wire 32 ( src2 [31:0] $end
   $var wire 1 ) branched $end
   $var wire 1 # equal $end
   $var wire 1 $ slt $end
   $var wire 1 % sltu $end
  $upscope $end
 $upscope $end
$enddefinitions $end


#0
1#
0$
0%
b000 &
b00000000000000000000000000000101 '
b00000000000000000000000000000101 (
1)
#1
b11111111111111111111111111111111 '
b11111111111111111111111111111111 (
#2
0#
1$
b10000000000000000000000000000000 '
b00000000000000000000000000000001 (
0)
#3
0$
1%
b00000000000000000000000000000001 '
b10000000000000000000000000000000 (
#4
1$
b00000000000000000000000000000010 (
#5
0$
0%
b11111111111111111111111111111110 '
b11111111111111111111111111111101 (
#6
1#
b001 &
b00000000000000000000000000000101 '
b00000000000000000000000000000101 (
#7
b11111111111111111111111111111111 '
b11111111111111111111111111111111 (
#8
0#
1$
b10000000000000000000000000000000 '
b00000000000000000000000000000001 (
1)
#9
0$
1%
b00000000000000000000000000000001 '
b10000000000000000000000000000000 (
#10
1$
b00000000000000000000000000000010 (
#11
0$
0%
b11111111111111111111111111111110 '
b11111111111111111111111111111101 (
#12
1#
b010 &
b00000000000000000000000000000101 '
b00000000000000000000000000000101 (
0)
#13
b11111111111111111111111111111111 '
b11111111111111111111111111111111 (
#14
0#
1$
b10000000000000000000000000000000 '
b00000000000000000000000000000001 (
#15
0$
1%
b00000000000000000000000000000001 '
b10000000000000000000000000000000 (
#16
1$
b00000000000000000000000000000010 (
#17
0$
0%
b11111111111111111111111111111110 '
b11111111111111111111111111111101 (
#18
1#
b011 &
b00000000000000000000000000000101 '
b00000000000000000000000000000101 (
1)
#19
b11111111111111111111111111111111 '
b11111111111111111111111111111111 (
#20
0#
1$
b10000000000000000000000000000000 '
b00000000000000000000000000000001 (
#21
0$
1%
b00000000000000000000000000000001 '
b10000000000000000000000000000000 (
#22
1$
b00000000000000000000000000000010 (
#23
0$
0%
b11111111111111111111111111111110 '
b11111111111111111111111111111101 (
#24
1#
b100 &
b00000000000000000000000000000101 '
b00000000000000000000000000000101 (
0)
#25
b11111111111111111111111111111111 '
b11111111111111111111111111111111 (
#26
0#
1$
b10000000000000000000000000000000 '
b00000000000000000000000000000001 (
1)
#27
0$
1%
b00000000000000000000000000000001 '
b10000000000000000000000000000000 (
0)
#28
1$
b00000000000000000000000000000010 (
1)
#29
0$
0%
b11111111111111111111111111111110 '
b11111111111111111111111111111101 (
0)
#30
1#
b101 &
b00000000000000000000000000000101 '
b00000000000000000000000000000101 (
1)
#31
b11111111111111111111111111111111 '
b11111111111111111111111111111111 (
#32
0#
1$
b10000000000000000000000000000000 '
b00000000000000000000000000000001 (
0)
#33
0$
1%
b00000000000000000000000000000001 '
b10000000000000000000000000000000 (
1)
#34
1$
b00000000000000000000000000000010 (
0)
#35
0$
0%
b11111111111111111111111111111110 '
b11111111111111111111111111111101 (
1)
#36
1#
b110 &
b00000000000000000000000000000101 '
b00000000000000000000000000000101 (
0)
#37
b11111111111111111111111111111111 '
b11111111111111111111111111111111 (
#38
0#
1$
b10000000000000000000000000000000 '
b00000000000000000000000000000001 (
#39
0$
1%
b00000000000000000000000000000001 '
b10000000000000000000000000000000 (
1)
#40
1$
b00000000000000000000000000000010 (
#41
0$
0%
b11111111111111111111111111111110 '
b11111111111111111111111111111101 (
0)
#42
1#
b111 &
b00000000000000000000000000000101 '
b00000000000000000000000000000101 (
1)
#43
b11111111111111111111111111111111 '
b11111111111111111111111111111111 (
#44
0#
1$
b10000000000000000000000000000000 '
b00000000000000000000000000000001 (
#45
0$
1%
b00000000000000000000000000000001 '
b10000000000000000000000000000000 (
0)
#46
1$
b00000000000000000000000000000010 (
#47
0$
0%
b11111111111111111111111111111110 '
b11111111111111111111111111111101 (
1)
