src/DataMem.sv
module DataMem#(
    parameter WORDS = 128,
    parameter mem_init = ""
) (
    input  logic        clk, wen,
    input  logic [31:0] address, wdata,
    input  logic [2:0]  byte_mask,

    output logic [31:0] rdata
);

    typedef enum logic [2:0] {
        LB  = 3'b000,
        LH  = 3'b001,
        LW  = 3'b010,
        LBU = 3'b100,
        LHU = 3'b101
    } byte_masks;

    reg [7:0] mem [0:(WORDS * 4) - 1];

    // Initialization
    initial begin
        if (mem_init != "")
            $readmemh(mem_init, mem);
        else
            for (int i = 0; i < (WORDS * 4); i++)
                mem[i] = 8'b0;
    end

    // Write (synchronous)
    always @(posedge clk) begin
        if (wen && address < WORDS * 4) begin
            case (byte_mask)
                LW: begin
                    mem[address + 0] <= wdata[7:0];
                    mem[address + 1] <= wdata[15:8];
                    mem[address + 2] <= wdata[23:16];
                    mem[address + 3] <= wdata[31:24];
                end
                LH, LHU: begin
                    mem[address + 0] <= wdata[7:0];
                    mem[address + 1] <= wdata[15:8];
                end
                LB, LBU: begin
                    mem[address + 0] <= wdata[7:0];
                end
                default: begin
                    mem[address + 0] <= wdata[7:0];
                    mem[address + 1] <= wdata[15:8];
                    mem[address + 2] <= wdata[23:16];
                    mem[address + 3] <= wdata[31:24];
                end
            endcase
        end
    end

    // Read (asynchronous)
    always_comb begin
        if (address >= WORDS * 4) begin
            rdata = 32'hDEADBEEF;
        end else begin
            case (byte_mask)
                LW: begin
                    rdata = {mem[address + 3], mem[address + 2], mem[address + 1], mem[address]};
                end
                LH: begin
                    rdata = {{16{mem[address + 1][7]}}, mem[address + 1], mem[address]};  // sign-extend
                end
                LHU: begin
                    rdata = {16'd0, mem[address + 1], mem[address]};
                end
                LB: begin
                    rdata = {{24{mem[address][7]}}, mem[address]};  // sign-extend
                end
                LBU: begin
                    rdata = {24'd0, mem[address]};
                end
                default: begin
                    rdata = {mem[address + 3], mem[address + 2], mem[address + 1], mem[address]};
                end
            endcase
        end
    end
endmodule

VCD/DataMem_waveform.vcd
$version Generated by VerilatedVcd $end
$timescale 1ps $end
 $scope module TOP $end
  $var wire 1 $ clk $end
  $var wire 1 % wen $end
  $var wire 32 & address [31:0] $end
  $var wire 32 ' wdata [31:0] $end
  $var wire 3 ( byte_mask [2:0] $end
  $var wire 32 ) rdata [31:0] $end
  $scope module DataMem $end
   $var wire 32 * WORDS [31:0] $end
   $var wire 8 + mem_init [7:0] $end
   $var wire 1 $ clk $end
   $var wire 1 % wen $end
   $var wire 32 & address [31:0] $end
   $var wire 32 ' wdata [31:0] $end
   $var wire 3 ( byte_mask [2:0] $end
   $var wire 32 ) rdata [31:0] $end
   $scope module unnamedblk1 $end
    $var wire 32 # i [31:0] $end
   $upscope $end
  $upscope $end
 $upscope $end
$enddefinitions $end


#0
b00000000000000000000001000000000 #
0$
1%
b00000000000000000000000000000000 &
b00010010001101000101011001111000 '
b010 (
b00000000000000000000000000000000 )
b00000000000000000000000010000000 *
b00000000 +
#1
1$
b00010010001101000101011001111000 )
#2
0$
0%
b00000000000000000000000000000000 '
#3
1$
#4
0$
1%
b00000000000000000000000000000100 &
b11111110110111001011101010011000 '
b00000000000000000000000000000000 )
#5
1$
b11111110110111001011101010011000 )
#6
0$
0%
b00000000000000000000000000000000 '
#7
1$
#8
0$
1%
b00000000000000000000000000001000 &
b00000000000000000001001000110100 '
b001 (
b00000000000000000000000000000000 )
#9
1$
b00000000000000000001001000110100 )
#10
0$
0%
b00000000000000000000000000000000 '
#11
1$
#12
0$
1%
b00000000000000000000000000001100 &
b00000000000000001010101111001101 '
b00000000000000000000000000000000 )
#13
1$
b11111111111111111010101111001101 )
#14
0$
0%
b00000000000000000000000000000000 '
#15
1$
#16
0$
1%
b00000000000000000000000000010000 &
b00000000000000001010101111001101 '
b101 (
b00000000000000000000000000000000 )
#17
1$
b00000000000000001010101111001101 )
#18
0$
0%
b00000000000000000000000000000000 '
#19
1$
#20
0$
1%
b00000000000000000000000000010100 &
b00000000000000000111111111111111 '
b00000000000000000000000000000000 )
#21
1$
b00000000000000000111111111111111 )
#22
0$
0%
b00000000000000000000000000000000 '
#23
1$
#24
0$
1%
b00000000000000000000000000011000 &
b00000000000000000000000001111000 '
b000 (
b00000000000000000000000000000000 )
#25
1$
b00000000000000000000000001111000 )
#26
0$
0%
b00000000000000000000000000000000 '
#27
1$
#28
0$
1%
b00000000000000000000000000011100 &
b00000000000000000000000011000001 '
b00000000000000000000000000000000 )
#29
1$
b11111111111111111111111111000001 )
#30
0$
0%
b00000000000000000000000000000000 '
#31
1$
#32
0$
1%
b00000000000000000000000000100000 &
b00000000000000000000000011000001 '
b100 (
b00000000000000000000000000000000 )
#33
1$
b00000000000000000000000011000001 )
#34
0$
0%
b00000000000000000000000000000000 '
#35
1$
#36
0$
1%
b00000000000000000000000000100100 &
b00000000000000000000000000011010 '
b00000000000000000000000000000000 )
#37
1$
b00000000000000000000000000011010 )
#38
0$
0%
b00000000000000000000000000000000 '
#39
1$
#40
0$
b00000000000000000000001000000000 &
b010 (
b11011110101011011011111011101111 )
#41
1$
#42
0$
1%
b00010010001101000101011001111000 '
