src/InstrMem.sv
module InstrMem#(
    parameter WORDS = 128,
    parameter mem_init = "./src/InstrMem_test.mem"
) (
    input logic [31:0] address,
    output logic [31:0] instr
);

    // Memory array: stores bytes, total size is WORDS * 4 bytes
    reg [7:0] mem[0:(WORDS * 4) - 1];

    initial begin
        if (mem_init != "") begin
            // Load memory contents from a hex file
            $readmemh(mem_init, mem);
        end else begin
            // Otherwise, initialize all memory locations to zero
            for (int i = 0; i < (WORDS * 4); i = i + 1) begin
                mem[i] = 8'h00;
            end
        end
    end

    always_comb begin
        // Read w/ EOF Flag
        instr = (address + 3) >= (WORDS * 4) ? 32'hDEADBEEF : {mem[address + 0],
                                                                mem[address + 1],
                                                                mem[address + 2],
                                                                mem[address + 3]};
    end

endmodule

VCD/InstrMem_waveform.vcd
$version Generated by VerilatedVcd $end
$timescale 1ps $end
 $scope module TOP $end
  $var wire 32 # address [31:0] $end
  $var wire 32 $ instr [31:0] $end
  $scope module InstrMem $end
   $var wire 32 % WORDS [31:0] $end
   $var wire 184 & mem_init [183:0] $end
   $var wire 32 # address [31:0] $end
   $var wire 32 $ instr [31:0] $end
  $upscope $end
 $upscope $end
$enddefinitions $end


#0
b00000000000000000000000000000000 #
b00000000000000000000000000000000 $
b00000000000000000000000010000000 %
b0010111000101111011100110111001001100011001011110100100101101110011100110111010001110010010011010110010101101101010111110111010001100101011100110111010000101110011011010110010101101101 &
#1
#2
b00000000000000000000000000000100 #
b00010010001101000101011001111000 $
#3
#4
b00000000000000000000000000001000 #
b10101010101110111100110011011101 $
#5
#6
b00000000000000000000000000001100 #
b00000000000000000000000000001100 $
#7
#8
b00000000000000000000000000100000 #
b00000000000000000000000000000000 $
#9
#10
b00000000000000000000000111111100 #
#11
#12
b00000000000000000000001000000000 #
b11011110101011011011111011101111 $
#13
#14
b00000000000000000000001000000100 #
